basicrpg/__init__.py
basicrpg/art.py
basicrpg/basics.py
basicrpg/components.py
basicrpg/errors.py
basicrpg/generators.py
basicrpg/items.py
basicrpg-0.3.5.dist-info/licenses/LICENSE
basicrpg-0.3.5.dist-info/METADATA
basicrpg-0.3.5.dist-info/WHEEL
basicrpg-0.3.5.dist-info/top_level.txt
basicrpg-0.3.5.dist-info/RECORD
