Metadata-Version: 2.4
Name: basicrpg
Version: 0.3.5
Summary: Python library for making RPG games, clean and easy.
Home-page: https://github.com/Unlisted27/basicrpglib
Author: Unlisted_dev
Classifier: Programming Language :: Python :: 3
Classifier: License :: OSI Approved :: MIT License
Classifier: Operating System :: OS Independent
Requires-Python: >=3.6
License-File: LICENSE
Dynamic: author
Dynamic: classifier
Dynamic: description
Dynamic: description-content-type
Dynamic: home-page
Dynamic: license-file
Dynamic: requires-python
Dynamic: summary
